requests_mv_integrations/__init__.py
requests_mv_integrations/request_mv_integration.py
requests_mv_integrations/request_mv_integration_download.py
requests_mv_integrations/request_mv_integration_upload.py
requests_mv_integrations/errors/__init__.py
requests_mv_integrations/errors/error_codes.py
requests_mv_integrations/errors/error_desc.py
requests_mv_integrations/errors/errors_traceback.py
requests_mv_integrations/exceptions/__init__.py
requests_mv_integrations/exceptions/base.py
requests_mv_integrations/exceptions/custom.py
requests_mv_integrations/support/__init__.py
requests_mv_integrations/support/bom_encoding.py
requests_mv_integrations/support/constants.py
requests_mv_integrations/support/curl.py
requests_mv_integrations/support/metrics.py
requests_mv_integrations/support/retry_exception.py
requests_mv_integrations/support/tune_request.py
requests_mv_integrations/support/usage.py
requests_mv_integrations/support/utils.py
requests_mv_integrations/support/response/__init__.py
requests_mv_integrations/support/response/csv.py
requests_mv_integrations/support/response/parse.py
requests_mv_integrations/support/response/validate.py
requests_mv_integrations-0.8.0.dist-info/DESCRIPTION.rst
requests_mv_integrations-0.8.0.dist-info/METADATA
requests_mv_integrations-0.8.0.dist-info/RECORD
requests_mv_integrations-0.8.0.dist-info/WHEEL
requests_mv_integrations-0.8.0.dist-info/metadata.json
requests_mv_integrations-0.8.0.dist-info/top_level.txt
