Metadata-Version: 2.0
Name: requests-mv-integrations
Version: 0.8.0
Summary: Extension of Python HTTP `requests` with verbose logging using `logging-mv-integrations`.
Home-page: https://github.com/TuneLab/requests-mv-integrations
Author: TUNE Inc.
Author-email: jefft@tune.com
License: MIT License
Download-URL: https://github.com/TuneLab/requests-mv-integrations/archive/v0.8.0.tar.gz
Keywords: requests tune multiverse
Platform: UNKNOWN
Classifier: Development Status :: 5 - Production/Stable
Classifier: Intended Audience :: Developers
Classifier: Natural Language :: English
Classifier: License :: OSI Approved :: MIT License
Classifier: Programming Language :: Python
Classifier: Programming Language :: Python :: 3.3
Classifier: Programming Language :: Python :: 3.4
Classifier: Programming Language :: Python :: 3.5
Classifier: Programming Language :: Python :: 3.6
Classifier: Programming Language :: Python :: Implementation :: PyPy
Requires-Dist: beautifulsoup4 (>=4.5.3)
Requires-Dist: DateTime (>=4.1.1)
Requires-Dist: deepdiff (>=3.3.0)
Requires-Dist: httpbin (>=0.6.2)
Requires-Dist: logging-mv-integrations (>=0.5.4)
Requires-Dist: pprintpp (>=0.3.0)
Requires-Dist: psutil (>=5.0.1)
Requires-Dist: pyhttpstatus-utils (==0.3.3)
Requires-Dist: pymemcache-client (==0.3.2)
Requires-Dist: pytest-cov (>=2.5.1)
Requires-Dist: pytest-forked (>=0.2)
Requires-Dist: pytest-httpbin (>=0.3.0)
Requires-Dist: pytest-mock (>=1.6.3)
Requires-Dist: pytest-xdist (>=1.20.1)
Requires-Dist: pytest (>=3.2.5)
Requires-Dist: python-dateutil (>=2.6.0)
Requires-Dist: requests-mock (>=1.3.0)
Requires-Dist: requests-toolbelt (>=0.7.1)
Requires-Dist: requests (>=2.18.4)
Requires-Dist: safe-cast (>=0.3.0)
Requires-Dist: six (>=1.10.0)
Requires-Dist: tzlocal (>=1.3)
Requires-Dist: ujson (>=1.35)
Requires-Dist: wheel (>=0.29.0)
Requires-Dist: xmltodict (>=0.10.2)
